odoo/addons/helpdesk_ticket_contract_contract/CHANGELOG.md
odoo/addons/helpdesk_ticket_contract_contract/README.rst
odoo/addons/helpdesk_ticket_contract_contract/__init__.py
odoo/addons/helpdesk_ticket_contract_contract/__manifest__.py
odoo/addons/helpdesk_ticket_contract_contract/i18n/ca_ES.po
odoo/addons/helpdesk_ticket_contract_contract/i18n/es.po
odoo/addons/helpdesk_ticket_contract_contract/models/__init__.py
odoo/addons/helpdesk_ticket_contract_contract/models/contract.py
odoo/addons/helpdesk_ticket_contract_contract/models/helpdesk_ticket.py
odoo/addons/helpdesk_ticket_contract_contract/static/description/contract.png
odoo/addons/helpdesk_ticket_contract_contract/static/description/icon.png
odoo/addons/helpdesk_ticket_contract_contract/static/description/ticket.png
odoo/addons/helpdesk_ticket_contract_contract/tests/__init__.py
odoo/addons/helpdesk_ticket_contract_contract/tests/test_contract.py
odoo/addons/helpdesk_ticket_contract_contract/tests/test_helpdesk_ticket.py
odoo/addons/helpdesk_ticket_contract_contract/views/contract_contract.xml
odoo/addons/helpdesk_ticket_contract_contract/views/helpdesk_ticket.xml
odoo_addon_helpdesk_ticket_contract_contract-16.0.1.0.0.dist-info/METADATA
odoo_addon_helpdesk_ticket_contract_contract-16.0.1.0.0.dist-info/WHEEL
odoo_addon_helpdesk_ticket_contract_contract-16.0.1.0.0.dist-info/top_level.txt
odoo_addon_helpdesk_ticket_contract_contract-16.0.1.0.0.dist-info/RECORD
